bsonstream/__init__.py
bsonstream-0.1.8.dist-info/licenses/LICENSE
bsonstream-0.1.8.dist-info/METADATA
bsonstream-0.1.8.dist-info/WHEEL
bsonstream-0.1.8.dist-info/top_level.txt
bsonstream-0.1.8.dist-info/RECORD
