Metadata-Version: 2.4
Name: bsonstream
Version: 0.1.8
Summary: BSON stream raw data into dict or individual BSON format - python
Project-URL: GitHub, https://github.com/bauman/python-bson-streaming
Requires-Python: >=3.8
License-File: LICENSE
Requires-Dist: pymongo~=4.15.2
Dynamic: license-file
